[{"code":"0210000","prefecture_code":3,"town":"","city_name":"一関市"},{"code":"0210853","prefecture_code":3,"town":"相去","city_name":"一関市"},{"code":"0210031","prefecture_code":3,"town":"青葉","city_name":"一関市"},{"code":"0210041","prefecture_code":3,"town":"赤荻","city_name":"一関市"},{"code":"0210864","prefecture_code":3,"town":"旭町","city_name":"一関市"},{"code":"0210008","prefecture_code":3,"town":"石畑","city_name":"一関市"},{"code":"0210894","prefecture_code":3,"town":"磐井町","city_name":"一関市"},{"code":"0210834","prefecture_code":3,"town":"宇南","city_name":"一関市"},{"code":"0210867","prefecture_code":3,"town":"駅前","city_name":"一関市"},{"code":"0210884","prefecture_code":3,"town":"大手町","city_name":"一関市"},{"code":"0210881","prefecture_code":3,"town":"大町","city_name":"一関市"},{"code":"0210882","prefecture_code":3,"town":"上大槻街","city_name":"一関市"},{"code":"0210007","prefecture_code":3,"town":"上日照","city_name":"一関市"},{"code":"0210833","prefecture_code":3,"town":"柄貝","city_name":"一関市"},{"code":"0210802","prefecture_code":3,"town":"北十軒街","city_name":"一関市"},{"code":"0210814","prefecture_code":3,"town":"北ほうりょう","city_name":"一関市"},{"code":"0210811","prefecture_code":3,"town":"久保","city_name":"一関市"},{"code":"0210101","prefecture_code":3,"town":"厳美町","city_name":"一関市"},{"code":"0210804","prefecture_code":3,"town":"五十人町","city_name":"一関市"},{"code":"0210022","prefecture_code":3,"town":"五代町","city_name":"一関市"},{"code":"0210052","prefecture_code":3,"town":"寿町","city_name":"一関市"},{"code":"0210024","prefecture_code":3,"town":"幸町","city_name":"一関市"},{"code":"0210891","prefecture_code":3,"town":"桜木町","city_name":"一関市"},{"code":"0210801","prefecture_code":3,"town":"桜街","city_name":"一関市"},{"code":"0210852","prefecture_code":3,"town":"沢","city_name":"一関市"},{"code":"0210832","prefecture_code":3,"town":"散田","city_name":"一関市"},{"code":"0210821","prefecture_code":3,"town":"三関","city_name":"一関市"},{"code":"0210893","prefecture_code":3,"town":"地主町","city_name":"一関市"},{"code":"0210806","prefecture_code":3,"town":"下大槻街","city_name":"一関市"},{"code":"0210877","prefecture_code":3,"town":"城内","city_name":"一関市"},{"code":"0210006","prefecture_code":3,"town":"上坊","city_name":"一関市"},{"code":"0210883","prefecture_code":3,"town":"新大町","city_name":"一関市"},{"code":"0210001","prefecture_code":3,"town":"新町","city_name":"一関市"},{"code":"0210841","prefecture_code":3,"town":"吸川街","city_name":"一関市"},{"code":"0210032","prefecture_code":3,"town":"末広","city_name":"一関市"},{"code":"0210851","prefecture_code":3,"town":"関が丘","city_name":"一関市"},{"code":"0210873","prefecture_code":3,"town":"台町","city_name":"一関市"},{"code":"0210875","prefecture_code":3,"town":"高崎町","city_name":"一関市"},{"code":"0210027","prefecture_code":3,"town":"竹山町","city_name":"一関市"},{"code":"0210885","prefecture_code":3,"town":"田村町","city_name":"一関市"},{"code":"0210844","prefecture_code":3,"town":"反町","city_name":"一関市"},{"code":"0210021","prefecture_code":3,"town":"中央町","city_name":"一関市"},{"code":"0210862","prefecture_code":3,"town":"千代田町","city_name":"一関市"},{"code":"0210874","prefecture_code":3,"town":"釣山","city_name":"一関市"},{"code":"0210023","prefecture_code":3,"town":"銅谷町","city_name":"一関市"},{"code":"0210005","prefecture_code":3,"town":"中里","city_name":"一関市"},{"code":"0210002","prefecture_code":3,"town":"中里","city_name":"一関市"},{"code":"0210836","prefecture_code":3,"town":"鳴神","city_name":"一関市"},{"code":"0210865","prefecture_code":3,"town":"新山","city_name":"一関市"},{"code":"0210854","prefecture_code":3,"town":"西沢","city_name":"一関市"},{"code":"0210835","prefecture_code":3,"town":"二本木","city_name":"一関市"},{"code":"0210831","prefecture_code":3,"town":"沼田","city_name":"一関市"},{"code":"0210102","prefecture_code":3,"town":"八幡、山ノ沢）","city_name":"一関市"},{"code":"0210902","prefecture_code":3,"town":"萩荘","city_name":"一関市"},{"code":"0210861","prefecture_code":3,"town":"機織山","city_name":"一関市"},{"code":"0210871","prefecture_code":3,"town":"八幡町","city_name":"一関市"},{"code":"0210807","prefecture_code":3,"town":"東花王町","city_name":"一関市"},{"code":"0210003","prefecture_code":3,"town":"東五代","city_name":"一関市"},{"code":"0210892","prefecture_code":3,"town":"東地主町","city_name":"一関市"},{"code":"0210822","prefecture_code":3,"town":"東台","city_name":"一関市"},{"code":"0210876","prefecture_code":3,"town":"広街","city_name":"一関市"},{"code":"0210812","prefecture_code":3,"town":"樋渡","city_name":"一関市"},{"code":"0210843","prefecture_code":3,"town":"深町","city_name":"一関市"},{"code":"0210221","prefecture_code":3,"town":"舞川","city_name":"一関市"},{"code":"0210901","prefecture_code":3,"town":"真柴","city_name":"一関市"},{"code":"0210004","prefecture_code":3,"town":"町浦","city_name":"一関市"},{"code":"0210803","prefecture_code":3,"town":"南十軒街","city_name":"一関市"},{"code":"0210866","prefecture_code":3,"town":"南新町","city_name":"一関市"},{"code":"0210813","prefecture_code":3,"town":"南ほうりょう","city_name":"一関市"},{"code":"0210863","prefecture_code":3,"town":"南町","city_name":"一関市"},{"code":"0210872","prefecture_code":3,"town":"宮坂町","city_name":"一関市"},{"code":"0210013","prefecture_code":3,"town":"宮下町","city_name":"一関市"},{"code":"0210012","prefecture_code":3,"town":"宮前町","city_name":"一関市"},{"code":"0210842","prefecture_code":3,"town":"柳町","city_name":"一関市"},{"code":"0210063","prefecture_code":3,"town":"山目","city_name":"一関市"},{"code":"0210035","prefecture_code":3,"town":"山目","city_name":"一関市"},{"code":"0210054","prefecture_code":3,"town":"山目","city_name":"一関市"},{"code":"0210033","prefecture_code":3,"town":"山目","city_name":"一関市"},{"code":"0210064","prefecture_code":3,"town":"山目","city_name":"一関市"},{"code":"0210051","prefecture_code":3,"town":"山目","city_name":"一関市"},{"code":"0210036","prefecture_code":3,"town":"山目","city_name":"一関市"},{"code":"0210034","prefecture_code":3,"town":"山目","city_name":"一関市"},{"code":"0210061","prefecture_code":3,"town":"山目","city_name":"一関市"},{"code":"0210062","prefecture_code":3,"town":"山目","city_name":"一関市"},{"code":"0210055","prefecture_code":3,"town":"山目","city_name":"一関市"},{"code":"0210056","prefecture_code":3,"town":"山目","city_name":"一関市"},{"code":"0210053","prefecture_code":3,"town":"山目","city_name":"一関市"},{"code":"0210026","prefecture_code":3,"town":"山目","city_name":"一関市"},{"code":"0210025","prefecture_code":3,"town":"山目","city_name":"一関市"},{"code":"0210011","prefecture_code":3,"town":"山目町","city_name":"一関市"},{"code":"0210805","prefecture_code":3,"town":"豊町","city_name":"一関市"},{"code":"0210815","prefecture_code":3,"town":"要害","city_name":"一関市"},{"code":"0210014","prefecture_code":3,"town":"蘭梅町","city_name":"一関市"},{"code":"0210102","prefecture_code":3,"town":"萩荘（赤猪子、芦ノ口、甘蕨、老流、大沢、上宇津野、上本郷、上要害、化粧坂、三月田、下宇津野、下本郷、外山、堂の沢、栃倉、栃倉南、長倉、中沢、八森、馬場、広面、平場、古釜場、曲淵、松原、南沢、谷起、焼切、八瀬、","city_name":"一関市"}]
