[{"code":"1810000","prefecture_code":13,"town":"","city_name":"三鷹市"},{"code":"1810011","prefecture_code":13,"town":"井口","city_name":"三鷹市"},{"code":"1810001","prefecture_code":13,"town":"井の頭","city_name":"三鷹市"},{"code":"1810015","prefecture_code":13,"town":"大沢","city_name":"三鷹市"},{"code":"1810012","prefecture_code":13,"town":"上連雀","city_name":"三鷹市"},{"code":"1810003","prefecture_code":13,"town":"北野","city_name":"三鷹市"},{"code":"1810013","prefecture_code":13,"town":"下連雀","city_name":"三鷹市"},{"code":"1810004","prefecture_code":13,"town":"新川","city_name":"三鷹市"},{"code":"1810016","prefecture_code":13,"town":"深大寺","city_name":"三鷹市"},{"code":"1810005","prefecture_code":13,"town":"中原","city_name":"三鷹市"},{"code":"1810014","prefecture_code":13,"town":"野崎","city_name":"三鷹市"},{"code":"1810002","prefecture_code":13,"town":"牟礼","city_name":"三鷹市"}]
