[{"code":"5570000","prefecture_code":27,"town":"","city_name":"大阪市西成区"},{"code":"5570032","prefecture_code":27,"town":"旭","city_name":"大阪市西成区"},{"code":"5570041","prefecture_code":27,"town":"岸里","city_name":"大阪市西成区"},{"code":"5570042","prefecture_code":27,"town":"岸里東","city_name":"大阪市西成区"},{"code":"5570061","prefecture_code":27,"town":"北津守","city_name":"大阪市西成区"},{"code":"5570021","prefecture_code":27,"town":"北開","city_name":"大阪市西成区"},{"code":"5570001","prefecture_code":27,"town":"山王","city_name":"大阪市西成区"},{"code":"5570052","prefecture_code":27,"town":"潮路","city_name":"大阪市西成区"},{"code":"5570012","prefecture_code":27,"town":"聖天下","city_name":"大阪市西成区"},{"code":"5570054","prefecture_code":27,"town":"千本中","city_name":"大阪市西成区"},{"code":"5570055","prefecture_code":27,"town":"千本南","city_name":"大阪市西成区"},{"code":"5570053","prefecture_code":27,"town":"千本北","city_name":"大阪市西成区"},{"code":"5570002","prefecture_code":27,"town":"太子","city_name":"大阪市西成区"},{"code":"5570051","prefecture_code":27,"town":"橘","city_name":"大阪市西成区"},{"code":"5570044","prefecture_code":27,"town":"玉出中","city_name":"大阪市西成区"},{"code":"5570043","prefecture_code":27,"town":"玉出東","city_name":"大阪市西成区"},{"code":"5570045","prefecture_code":27,"town":"玉出西","city_name":"大阪市西成区"},{"code":"5570062","prefecture_code":27,"town":"津守","city_name":"大阪市西成区"},{"code":"5570031","prefecture_code":27,"town":"鶴見橋","city_name":"大阪市西成区"},{"code":"5570024","prefecture_code":27,"town":"出城","city_name":"大阪市西成区"},{"code":"5570014","prefecture_code":27,"town":"天下茶屋","city_name":"大阪市西成区"},{"code":"5570011","prefecture_code":27,"town":"天下茶屋東","city_name":"大阪市西成区"},{"code":"5570003","prefecture_code":27,"town":"天下茶屋北","city_name":"大阪市西成区"},{"code":"5570013","prefecture_code":27,"town":"天神ノ森","city_name":"大阪市西成区"},{"code":"5570022","prefecture_code":27,"town":"中開","city_name":"大阪市西成区"},{"code":"5570025","prefecture_code":27,"town":"長橋","city_name":"大阪市西成区"},{"code":"5570033","prefecture_code":27,"town":"梅南","city_name":"大阪市西成区"},{"code":"5570004","prefecture_code":27,"town":"萩之茶屋","city_name":"大阪市西成区"},{"code":"5570015","prefecture_code":27,"town":"花園南","city_name":"大阪市西成区"},{"code":"5570016","prefecture_code":27,"town":"花園北","city_name":"大阪市西成区"},{"code":"5570034","prefecture_code":27,"town":"松","city_name":"大阪市西成区"},{"code":"5570063","prefecture_code":27,"town":"南津守","city_name":"大阪市西成区"},{"code":"5570023","prefecture_code":27,"town":"南開","city_name":"大阪市西成区"}]
