[{"code":"8820000","prefecture_code":45,"town":"","city_name":"延岡市"},{"code":"8820845","prefecture_code":45,"town":"安賀多町","city_name":"延岡市"},{"code":"8820847","prefecture_code":45,"town":"旭町","city_name":"延岡市"},{"code":"8820872","prefecture_code":45,"town":"愛宕町","city_name":"延岡市"},{"code":"8820871","prefecture_code":45,"town":"愛宕山","city_name":"延岡市"},{"code":"8820071","prefecture_code":45,"town":"天下町","city_name":"延岡市"},{"code":"8820025","prefecture_code":45,"town":"粟野名町","city_name":"延岡市"},{"code":"8820831","prefecture_code":45,"town":"出口町","city_name":"延岡市"},{"code":"8820856","prefecture_code":45,"town":"出北","city_name":"延岡市"},{"code":"8820003","prefecture_code":45,"town":"稲葉崎町","city_name":"延岡市"},{"code":"8820095","prefecture_code":45,"town":"浦城町","city_name":"延岡市"},{"code":"8820084","prefecture_code":45,"town":"宇和田町","city_name":"延岡市"},{"code":"8820046","prefecture_code":45,"town":"恵比須町","city_name":"延岡市"},{"code":"8820013","prefecture_code":45,"town":"追内町","city_name":"延岡市"},{"code":"8820001","prefecture_code":45,"town":"大峡町","city_name":"延岡市"},{"code":"8820027","prefecture_code":45,"town":"大門町","city_name":"延岡市"},{"code":"8820841","prefecture_code":45,"town":"大瀬町","city_name":"延岡市"},{"code":"8820024","prefecture_code":45,"town":"大武町","city_name":"延岡市"},{"code":"8820803","prefecture_code":45,"town":"大貫町","city_name":"延岡市"},{"code":"8820086","prefecture_code":45,"town":"大野町","city_name":"延岡市"},{"code":"8820056","prefecture_code":45,"town":"岡富町","city_name":"延岡市"},{"code":"8820057","prefecture_code":45,"town":"岡富山","city_name":"延岡市"},{"code":"8820075","prefecture_code":45,"town":"岡元町","city_name":"延岡市"},{"code":"8820876","prefecture_code":45,"town":"沖田町","city_name":"延岡市"},{"code":"8820006","prefecture_code":45,"town":"尾崎町","city_name":"延岡市"},{"code":"8820855","prefecture_code":45,"town":"卸本町","city_name":"延岡市"},{"code":"8820073","prefecture_code":45,"town":"貝の畑町","city_name":"延岡市"},{"code":"8820085","prefecture_code":45,"town":"鹿狩瀬町","city_name":"延岡市"},{"code":"8820004","prefecture_code":45,"town":"樫山町","city_name":"延岡市"},{"code":"8820012","prefecture_code":45,"town":"鹿小路","city_name":"延岡市"},{"code":"8820844","prefecture_code":45,"town":"春日町","city_name":"延岡市"},{"code":"8820877","prefecture_code":45,"town":"片田町","city_name":"延岡市"},{"code":"8820867","prefecture_code":45,"town":"構口町","city_name":"延岡市"},{"code":"8820833","prefecture_code":45,"town":"上大瀬町","city_name":"延岡市"},{"code":"8820885","prefecture_code":45,"town":"上三輪町","city_name":"延岡市"},{"code":"8820017","prefecture_code":45,"town":"川島町","city_name":"延岡市"},{"code":"8820033","prefecture_code":45,"town":"川原崎町","city_name":"延岡市"},{"code":"8820043","prefecture_code":45,"town":"祗園町","city_name":"延岡市"},{"code":"8820121","prefecture_code":45,"town":"北方町板上","city_name":"延岡市"},{"code":"8820122","prefecture_code":45,"town":"北方町板下","city_name":"延岡市"},{"code":"8820123","prefecture_code":45,"town":"北方町うそ越","city_name":"延岡市"},{"code":"8820106","prefecture_code":45,"town":"北方町笠下","city_name":"延岡市"},{"code":"8820126","prefecture_code":45,"town":"北方町上崎","city_name":"延岡市"},{"code":"8820231","prefecture_code":45,"town":"北方町上鹿川","city_name":"延岡市"},{"code":"8820125","prefecture_code":45,"town":"北方町川水流","city_name":"延岡市"},{"code":"8820129","prefecture_code":45,"town":"北方町北久保山","city_name":"延岡市"},{"code":"8820127","prefecture_code":45,"town":"北方町蔵田","city_name":"延岡市"},{"code":"8820241","prefecture_code":45,"town":"北方町三ケ村","city_name":"延岡市"},{"code":"8820237","prefecture_code":45,"town":"北方町椎畑","city_name":"延岡市"},{"code":"8820232","prefecture_code":45,"town":"北方町下鹿川","city_name":"延岡市"},{"code":"8820233","prefecture_code":45,"town":"北方町菅原","city_name":"延岡市"},{"code":"8820124","prefecture_code":45,"town":"北方町曽木","city_name":"延岡市"},{"code":"8820238","prefecture_code":45,"town":"北方町滝下","city_name":"延岡市"},{"code":"8820104","prefecture_code":45,"town":"北方町角田","city_name":"延岡市"},{"code":"8820245","prefecture_code":45,"town":"北方町早上","city_name":"延岡市"},{"code":"8820244","prefecture_code":45,"town":"北方町早中","city_name":"延岡市"},{"code":"8820243","prefecture_code":45,"town":"北方町早日渡","city_name":"延岡市"},{"code":"8820236","prefecture_code":45,"town":"北方町日平","city_name":"延岡市"},{"code":"8820107","prefecture_code":45,"town":"北方町藤の木","city_name":"延岡市"},{"code":"8820101","prefecture_code":45,"town":"北方町二股","city_name":"延岡市"},{"code":"8820235","prefecture_code":45,"town":"北方町槇峰","city_name":"延岡市"},{"code":"8820128","prefecture_code":45,"town":"北方町南久保山","city_name":"延岡市"},{"code":"8820234","prefecture_code":45,"town":"北方町美々地","city_name":"延岡市"},{"code":"8820242","prefecture_code":45,"town":"北方町八峡","city_name":"延岡市"},{"code":"8820097","prefecture_code":45,"town":"北川町川内名","city_name":"延岡市"},{"code":"8820041","prefecture_code":45,"town":"北小路","city_name":"延岡市"},{"code":"8820834","prefecture_code":45,"town":"北新小路","city_name":"延岡市"},{"code":"8820814","prefecture_code":45,"town":"北町","city_name":"延岡市"},{"code":"8820873","prefecture_code":45,"town":"共栄町","city_name":"延岡市"},{"code":"8820091","prefecture_code":45,"town":"桑平町","city_name":"延岡市"},{"code":"8820093","prefecture_code":45,"town":"神戸町","city_name":"延岡市"},{"code":"8820076","prefecture_code":45,"town":"小川町","city_name":"延岡市"},{"code":"8820882","prefecture_code":45,"town":"小野町","city_name":"延岡市"},{"code":"8820061","prefecture_code":45,"town":"小峰町","city_name":"延岡市"},{"code":"8820047","prefecture_code":45,"town":"紺屋町","city_name":"延岡市"},{"code":"8820832","prefecture_code":45,"town":"西小路","city_name":"延岡市"},{"code":"8820053","prefecture_code":45,"town":"幸町","city_name":"延岡市"},{"code":"8820054","prefecture_code":45,"town":"栄町","city_name":"延岡市"},{"code":"8820007","prefecture_code":45,"town":"桜ケ丘","city_name":"延岡市"},{"code":"8820816","prefecture_code":45,"town":"桜小路","city_name":"延岡市"},{"code":"8820036","prefecture_code":45,"town":"桜園町","city_name":"延岡市"},{"code":"8820002","prefecture_code":45,"town":"差木野町","city_name":"延岡市"},{"code":"8820081","prefecture_code":45,"town":"佐野町","city_name":"延岡市"},{"code":"8820864","prefecture_code":45,"town":"塩浜町","city_name":"延岡市"},{"code":"8820096","prefecture_code":45,"town":"島浦町","city_name":"延岡市"},{"code":"8820883","prefecture_code":45,"town":"下三輪町","city_name":"延岡市"},{"code":"8820034","prefecture_code":45,"town":"昭和町","city_name":"延岡市"},{"code":"8820014","prefecture_code":45,"town":"白石町","city_name":"延岡市"},{"code":"8820835","prefecture_code":45,"town":"新小路","city_name":"延岡市"},{"code":"8820827","prefecture_code":45,"town":"新町","city_name":"延岡市"},{"code":"8820011","prefecture_code":45,"town":"須佐町","city_name":"延岡市"},{"code":"8820825","prefecture_code":45,"town":"須崎町","city_name":"延岡市"},{"code":"8820045","prefecture_code":45,"town":"瀬之口町","city_name":"延岡市"},{"code":"8820857","prefecture_code":45,"town":"惣領町","city_name":"延岡市"},{"code":"8820042","prefecture_code":45,"town":"高千穂通","city_name":"延岡市"},{"code":"8820064","prefecture_code":45,"town":"高野町","city_name":"延岡市"},{"code":"8820874","prefecture_code":45,"town":"伊達町","city_name":"延岡市"},{"code":"8820824","prefecture_code":45,"town":"中央通","city_name":"延岡市"},{"code":"8820836","prefecture_code":45,"town":"恒富町","city_name":"延岡市"},{"code":"8820865","prefecture_code":45,"town":"鶴ケ丘","city_name":"延岡市"},{"code":"8820811","prefecture_code":45,"town":"天神小路","city_name":"延岡市"},{"code":"8820016","prefecture_code":45,"town":"東海町","city_name":"延岡市"},{"code":"8820051","prefecture_code":45,"town":"富美山町","city_name":"延岡市"},{"code":"8820031","prefecture_code":45,"town":"中川原町","city_name":"延岡市"},{"code":"8820846","prefecture_code":45,"town":"中島町","city_name":"延岡市"},{"code":"8820032","prefecture_code":45,"town":"中の瀬町","city_name":"延岡市"},{"code":"8820823","prefecture_code":45,"town":"中町","city_name":"延岡市"},{"code":"8820884","prefecture_code":45,"town":"中三輪町","city_name":"延岡市"},{"code":"8820843","prefecture_code":45,"town":"永池町","city_name":"延岡市"},{"code":"8820854","prefecture_code":45,"town":"長浜町","city_name":"延岡市"},{"code":"8820005","prefecture_code":45,"town":"夏田町","city_name":"延岡市"},{"code":"8820804","prefecture_code":45,"town":"西階町","city_name":"延岡市"},{"code":"8820802","prefecture_code":45,"town":"野地町","city_name":"延岡市"},{"code":"8820805","prefecture_code":45,"town":"野田","city_name":"延岡市"},{"code":"8820801","prefecture_code":45,"town":"野田町","city_name":"延岡市"},{"code":"8820052","prefecture_code":45,"town":"萩町","city_name":"延岡市"},{"code":"8820044","prefecture_code":45,"town":"博労町","city_name":"延岡市"},{"code":"8820851","prefecture_code":45,"town":"浜砂","city_name":"延岡市"},{"code":"8820862","prefecture_code":45,"town":"浜町","city_name":"延岡市"},{"code":"8820852","prefecture_code":45,"town":"東浜砂町","city_name":"延岡市"},{"code":"8820813","prefecture_code":45,"town":"東本小路","city_name":"延岡市"},{"code":"8820035","prefecture_code":45,"town":"日の出町","city_name":"延岡市"},{"code":"8820861","prefecture_code":45,"town":"別府町","city_name":"延岡市"},{"code":"8820065","prefecture_code":45,"town":"平田町","city_name":"延岡市"},{"code":"8820866","prefecture_code":45,"town":"平原町","city_name":"延岡市"},{"code":"8820022","prefecture_code":45,"town":"二ツ島町","city_name":"延岡市"},{"code":"8820826","prefecture_code":45,"town":"船倉町","city_name":"延岡市"},{"code":"8820063","prefecture_code":45,"town":"古川町","city_name":"延岡市"},{"code":"8820837","prefecture_code":45,"town":"古城町","city_name":"延岡市"},{"code":"8820853","prefecture_code":45,"town":"方財町","city_name":"延岡市"},{"code":"8820082","prefecture_code":45,"town":"祝子町","city_name":"延岡市"},{"code":"8820074","prefecture_code":45,"town":"細見町","city_name":"延岡市"},{"code":"8820812","prefecture_code":45,"town":"本小路","city_name":"延岡市"},{"code":"8820821","prefecture_code":45,"town":"本町","city_name":"延岡市"},{"code":"8820066","prefecture_code":45,"town":"舞野町","city_name":"延岡市"},{"code":"8820023","prefecture_code":45,"town":"牧町","city_name":"延岡市"},{"code":"8820062","prefecture_code":45,"town":"松山町","city_name":"延岡市"},{"code":"8820881","prefecture_code":45,"town":"三須町","city_name":"延岡市"},{"code":"8820015","prefecture_code":45,"town":"水尻町","city_name":"延岡市"},{"code":"8820842","prefecture_code":45,"town":"三ツ瀬町","city_name":"延岡市"},{"code":"8820863","prefecture_code":45,"town":"緑ケ丘","city_name":"延岡市"},{"code":"8820822","prefecture_code":45,"town":"南町","city_name":"延岡市"},{"code":"8820092","prefecture_code":45,"town":"宮長町","city_name":"延岡市"},{"code":"8820087","prefecture_code":45,"town":"妙町","city_name":"延岡市"},{"code":"8820077","prefecture_code":45,"town":"行縢町","city_name":"延岡市"},{"code":"8820021","prefecture_code":45,"town":"無鹿町","city_name":"延岡市"},{"code":"8820094","prefecture_code":45,"town":"安井町","city_name":"延岡市"},{"code":"8820815","prefecture_code":45,"town":"柳沢町","city_name":"延岡市"},{"code":"8820055","prefecture_code":45,"town":"山下町","city_name":"延岡市"},{"code":"8820037","prefecture_code":45,"town":"山月町","city_name":"延岡市"},{"code":"8820083","prefecture_code":45,"town":"柚木町","city_name":"延岡市"},{"code":"8820026","prefecture_code":45,"town":"柚の木田町","city_name":"延岡市"},{"code":"8820072","prefecture_code":45,"town":"吉野町","city_name":"延岡市"},{"code":"8820875","prefecture_code":45,"town":"若葉町","city_name":"延岡市"},{"code":"8821100","prefecture_code":45,"town":"","city_name":"西臼杵郡高千穂町"},{"code":"8821621","prefecture_code":45,"town":"岩戸","city_name":"西臼杵郡高千穂町"},{"code":"8821102","prefecture_code":45,"town":"押方","city_name":"西臼杵郡高千穂町"},{"code":"8821622","prefecture_code":45,"town":"上岩戸","city_name":"西臼杵郡高千穂町"},{"code":"8821411","prefecture_code":45,"town":"上野","city_name":"西臼杵郡高千穂町"},{"code":"8821414","prefecture_code":45,"town":"河内","city_name":"西臼杵郡高千穂町"},{"code":"8821415","prefecture_code":45,"town":"五ケ所","city_name":"西臼杵郡高千穂町"},{"code":"8821412","prefecture_code":45,"town":"下野","city_name":"西臼杵郡高千穂町"},{"code":"8821413","prefecture_code":45,"town":"田原","city_name":"西臼杵郡高千穂町"},{"code":"8821101","prefecture_code":45,"town":"三田井","city_name":"西臼杵郡高千穂町"},{"code":"8821103","prefecture_code":45,"town":"向山","city_name":"西臼杵郡高千穂町"},{"code":"8820400","prefecture_code":45,"town":"","city_name":"西臼杵郡日之影町"},{"code":"8820302","prefecture_code":45,"town":"岩井川","city_name":"西臼杵郡日之影町"},{"code":"8820402","prefecture_code":45,"town":"岩井川","city_name":"西臼杵郡日之影町"},{"code":"8820301","prefecture_code":45,"town":"西ノ内、舟ノ尾、八戸、簗崎）","city_name":"西臼杵郡日之影町"},{"code":"8820401","prefecture_code":45,"town":"七折","city_name":"西臼杵郡日之影町"},{"code":"8820403","prefecture_code":45,"town":"見立","city_name":"西臼杵郡日之影町"},{"code":"8820304","prefecture_code":45,"town":"分城","city_name":"西臼杵郡日之影町"},{"code":"8821200","prefecture_code":45,"town":"","city_name":"西臼杵郡五ヶ瀬町"},{"code":"8821201","prefecture_code":45,"town":"鞍岡","city_name":"西臼杵郡五ヶ瀬町"},{"code":"8821202","prefecture_code":45,"town":"桑野内","city_name":"西臼杵郡五ヶ瀬町"},{"code":"8821203","prefecture_code":45,"town":"三ヶ所","city_name":"西臼杵郡五ヶ瀬町"},{"code":"8820301","prefecture_code":45,"town":"七折（阿下、笠戸、椛木、鹿川、新町、滝ノ内、中川、","city_name":"西臼杵郡日之影町"}]
